gallery_dl_bytes/__init__.py
gallery_dl_bytes/_version.py
gallery_dl_bytes/downloader.py
gallery_dl_bytes/extra_types.py
gallery_dl_bytes/file.py
gallery_dl_bytes/job.py
gallery_dl_bytes/message.py
gallery_dl_bytes/py.typed
gallery_dl_bytes/util.py
gallery_dl_bytes-2.5.0.dist-info/METADATA
gallery_dl_bytes-2.5.0.dist-info/WHEEL
gallery_dl_bytes-2.5.0.dist-info/licenses/LICENSE
gallery_dl_bytes-2.5.0.dist-info/RECORD
