Metadata-Version: 2.4
Name: gallery-dl-bytes
Version: 2.5.0
Summary: API to download files directly to memory with gallery-dl
Project-URL: Source, https://github.com/thcrt/gallery-dl-bytes/
Project-URL: Issues, https://github.com/thcrt/gallery-dl-bytes/issues/
Project-URL: PyPI, https://pypi.org/project/gallery-dl-bytes/
Author-email: thcrt <110127860+thcrt@users.noreply.github.com>
License-Expression: GPL-2.0-only
License-File: LICENSE
Keywords: crawler,downloader,gallery,image,scraper
Classifier: Development Status :: 4 - Beta
Classifier: Intended Audience :: Developers
Classifier: License :: OSI Approved :: GNU General Public License v2 (GPLv2)
Classifier: Operating System :: OS Independent
Classifier: Programming Language :: Python
Classifier: Programming Language :: Python :: 3
Classifier: Programming Language :: Python :: 3 :: Only
Classifier: Programming Language :: Python :: 3.12
Classifier: Programming Language :: Python :: 3.13
Classifier: Topic :: Internet :: WWW/HTTP
Classifier: Topic :: Multimedia :: Graphics
Classifier: Topic :: Software Development :: Libraries
Classifier: Topic :: Software Development :: Libraries :: Python Modules
Classifier: Typing :: Typed
Requires-Python: >=3.12
Requires-Dist: gallery-dl>=1.28.5
